MANIFEST.in
README.md
setup.py
dummy_yummy.egg-info/PKG-INFO
dummy_yummy.egg-info/SOURCES.txt
dummy_yummy.egg-info/dependency_links.txt
dummy_yummy.egg-info/not-zip-safe
dummy_yummy.egg-info/top_level.txt
yummy/__init__.py