Metadata-Version: 1.0
Name: dummy-yummy
Version: 1.0.4
Summary: dummy-yummy is a dummy package used for testing automatic installation in virtualenvs with 3bot.
Home-page: https://github.com/arteria/dummy-yummy
Author: arteria GmbH
Author-email: admin@arteria.ch
License: BSD
Platform: UNKNOWN
